oculith/__init__.py
oculith/__main__.py
oculith/__version__.py
oculith/api/__init__.py
oculith/api/endpoints.py
oculith/core/__init__.py
oculith/core/converter.py
oculith/core/file_service.py
oculith/core/litellm.py
oculith/core/pipeline.py
oculith/core/queue_manager.py
oculith/core/retriever.py
oculith/core/schemas.py
oculith-0.1.3.dist-info/METADATA
oculith-0.1.3.dist-info/WHEEL
oculith-0.1.3.dist-info/entry_points.txt
oculith-0.1.3.dist-info/RECORD
