Metadata-Version: 2.3
Name: oculith
Version: 0.1.3
Summary: Document OCR based on docling
Author: arcstep
Author-email: 43801@qq.com
Requires-Python: >=3.11,<4.0
Classifier: Programming Language :: Python :: 3
Classifier: Programming Language :: Python :: 3.11
Classifier: Programming Language :: Python :: 3.12
Classifier: Programming Language :: Python :: 3.13
Requires-Dist: aiofiles (>=24.1.0,<25.0.0)
Requires-Dist: chromadb (>=1.0.4,<2.0.0)
Requires-Dist: diskcache (>=5.6.3,<6.0.0)
Requires-Dist: docling (>=2.30.0)
Requires-Dist: fastapi (>=0.68.0)
Requires-Dist: lancedb (>=0.21.2,<0.22.0)
Requires-Dist: litellm (>=1.66.0,<2.0.0)
Requires-Dist: loguru (>=0.5.3)
Requires-Dist: pyarrow (>=19.0.1,<20.0.0)
Requires-Dist: pydantic (>=1.8.2)
Requires-Dist: python-dotenv (>=0.19.0)
Requires-Dist: python-multipart (>=0.0.5)
Requires-Dist: soulseal (>=0.1.9,<0.2.0)
Requires-Dist: torch (>=2.0.0,<2.3)
Requires-Dist: uvicorn (>=0.15.0)
Requires-Dist: voidring (>=0.1.0)
